topsis/topsis.py
Topsis_RaghavNarula_101903795-1.0.0.dist-info/LICENSE
Topsis_RaghavNarula_101903795-1.0.0.dist-info/METADATA
Topsis_RaghavNarula_101903795-1.0.0.dist-info/WHEEL
Topsis_RaghavNarula_101903795-1.0.0.dist-info/entry_points.txt
Topsis_RaghavNarula_101903795-1.0.0.dist-info/top_level.txt
Topsis_RaghavNarula_101903795-1.0.0.dist-info/RECORD
