Metadata-Version: 2.1
Name: Topsis-RaghavNarula-101903795
Version: 1.0.0
Summary: It gives a csv file that includes the topsis result
Home-page: UNKNOWN
Author: Raghav Narula
Author-email: rnarula_be19@thapar.edu
License: MIT
Platform: UNKNOWN
Classifier: Programming Language :: Python :: 3.6
Classifier: Programming Language :: Python :: 3.7
Classifier: Programming Language :: Python :: 3.8
Classifier: Programming Language :: Python :: 3.8
Classifier: Programming Language :: Python :: 3.9
Requires-Dist: pandas
Requires-Dist: numpy
